{"type": "FeatureCollection", "columns": {"bkt_idx": "Number", "bucket": "Number", "date": "Date", "ts": "Number", "u": "<any>"}, "features": [{"type": "Feature", "geometry": {"type": "Point", "coordinates": [76.86758583571502, 9.989075553423989]}, "id": "0", "properties": {"bkt_idx": 1, "bucket": 2, "date": {"type": "Date", "value": 1596672361298}, "ts": 1596672361298.3662, "u": 0.10036065728329457}}, {"type": "Feature", "geometry": {"type": "Point", "coordinates": [76.99488064286626, 10.013007549555102]}, "id": "1", "properties": {"bkt_idx": 21, "bucket": 22, "date": {"type": "Date", "value": 1596675312065}, "ts": 1596675312065.4214, "u": 0.9200181726300426}}, {"type": "Feature", "geometry": {"type": "Point", "coordinates": [76.95378839877122, 10.119828204681953]}, "id": "2", "properties": {"bkt_idx": 8, "bucket": 9, "date": {"type": "Date", "value": 1596673483097}, "ts": 1596673483097.5012, "u": 0.4119715280988788}}, {"type": "Feature", "geometry": {"type": "Point", "coordinates": [76.889546763964, 9.95842885008843]}, "id": "3", "properties": {"bkt_idx": 13, "bucket": 14, "date": {"type": "Date", "value": 1596674124673}, "ts": 1596674124673.6226, "u": 0.5901871173981147}}, {"type": "Feature", "geometry": {"type": "Point", "coordinates": [77.01658591992904, 10.152572082625369]}, "id": "4", "properties": {"bkt_idx": 13, "bucket": 14, "date": {"type": "Date", "value": 1596674178861}, "ts": 1596674178861.3486, "u": 0.6052392635066076}}, {"type": "Feature", "geometry": {"type": "Point", "coordinates": [77.08729225524011, 9.96161406887432]}, "id": "5", "properties": {"bkt_idx": 5, "bucket": 6, "date": {"type": "Date", "value": 1596672950992}, "ts": 1596672950992.3357, "u": 0.26416453772291215}}, {"type": "Feature", "geometry": {"type": "Point", "coordinates": [76.96958706719525, 10.012936499379387]}, "id": "6", "properties": {"bkt_idx": 2, "bucket": 3, "date": {"type": "Date", "value": 1596672519047}, "ts": 1596672519047.7073, "u": 0.14417991868387692}}, {"type": "Feature", "geometry": {"type": "Point", "coordinates": [77.00526063352596, 10.005731224134244]}, "id": "7", "properties": {"bkt_idx": 17, "bucket": 18, "date": {"type": "Date", "value": 1596674751572}, "ts": 1596674751572.8516, "u": 0.7643257921085098}}, {"type": "Feature", "geometry": {"type": "Point", "coordinates": [76.92216697571995, 10.064938195649004]}, "id": "8", "properties": {"bkt_idx": 8, "bucket": 9, "date": {"type": "Date", "value": 1596673471716}, "ts": 1596673471716.1462, "u": 0.40881004064317694}}, {"type": "Feature", "geometry": {"type": "Point", "coordinates": [76.99167053575395, 10.01276191019975]}, "id": "9", "properties": {"bkt_idx": 3, "bucket": 4, "date": {"type": "Date", "value": 1596672707297}, "ts": 1596672707297.7505, "u": 0.19647159737191167}}, {"type": "Feature", "geometry": {"type": "Point", "coordinates": [77.03041972212165, 9.986302847364056]}, "id": "10", "properties": {"bkt_idx": 12, "bucket": 13, "date": {"type": "Date", "value": 1596673953649}, "ts": 1596673953649.3235, "u": 0.5426803676134667}}, {"type": "Feature", "geometry": {"type": "Point", "coordinates": [76.99069694786465, 10.029666647685762]}, "id": "11", "properties": {"bkt_idx": 8, "bucket": 9, "date": {"type": "Date", "value": 1596673432141}, "ts": 1596673432141.3474, "u": 0.3978170409435673}}, {"type": "Feature", "geometry": {"type": "Point", "coordinates": [77.0627002582475, 10.011336804451123]}, "id": "12", "properties": {"bkt_idx": 8, "bucket": 9, "date": {"type": "Date", "value": 1596673449247}, "ts": 1596673449247.0906, "u": 0.4025686362584999}}, {"type": "Feature", "geometry": {"type": "Point", "coordinates": [77.11853280406083, 9.973660821321914]}, "id": "13", "properties": {"bkt_idx": 14, "bucket": 15, "date": {"type": "Date", "value": 1596674306718}, "ts": 1596674306718.1995, "u": 0.6407550553853619}}, {"type": "Feature", "geometry": {"type": "Point", "coordinates": [76.88548990015248, 9.911713533849321]}, "id": "14", "properties": {"bkt_idx": 18, "bucket": 19, "date": {"type": "Date", "value": 1596674976694}, "ts": 1596674976694.4365, "u": 0.8268595657169047}}, {"type": "Feature", "geometry": {"type": "Point", "coordinates": [76.87573512078129, 10.091965475433511]}, "id": "15", "properties": {"bkt_idx": 11, "bucket": 12, "date": {"type": "Date", "value": 1596673905620}, "ts": 1596673905620.4832, "u": 0.5293390230706913}}, {"type": "Feature", "geometry": {"type": "Point", "coordinates": [77.0131127394414, 10.105443127413462]}, "id": "16", "properties": {"bkt_idx": 6, "bucket": 7, "date": {"type": "Date", "value": 1596673138265}, "ts": 1596673138265.4263, "u": 0.3161848406255192}}, {"type": "Feature", "geometry": {"type": "Point", "coordinates": [77.030198254117, 9.94469838330103]}, "id": "17", "properties": {"bkt_idx": 16, "bucket": 17, "date": {"type": "Date", "value": 1596674569400}, "ts": 1596674569400.97, "u": 0.7137224916712899}}, {"type": "Feature", "geometry": {"type": "Point", "coordinates": [76.89935180076456, 10.059174092781332]}, "id": "18", "properties": {"bkt_idx": 11, "bucket": 12, "date": {"type": "Date", "value": 1596673897269}, "ts": 1596673897269.5095, "u": 0.5270193081890242}}, {"type": "Feature", "geometry": {"type": "Point", "coordinates": [76.95148217573143, 10.126636932822109]}, "id": "19", "properties": {"bkt_idx": 0, "bucket": 1, "date": {"type": "Date", "value": 1596672224699}, "ts": 1596672224699.8826, "u": 0.06241663406390641}}, {"type": "Feature", "geometry": {"type": "Point", "coordinates": [77.10290249109234, 9.990019896894701]}, "id": "20", "properties": {"bkt_idx": 5, "bucket": 6, "date": {"type": "Date", "value": 1596672910948}, "ts": 1596672910948.307, "u": 0.2530411963595418}}, {"type": "Feature", "geometry": {"type": "Point", "coordinates": [76.88205829604998, 10.039259857876033]}, "id": "21", "properties": {"bkt_idx": 18, "bucket": 19, "date": {"type": "Date", "value": 1596674868331}, "ts": 1596674868331.3816, "u": 0.7967587171274209}}, {"type": "Feature", "geometry": {"type": "Point", "coordinates": [77.12355228126484, 9.976656791979718]}, "id": "22", "properties": {"bkt_idx": 9, "bucket": 10, "date": {"type": "Date", "value": 1596673597203}, "ts": 1596673597203.757, "u": 0.44366771032561403}}, {"type": "Feature", "geometry": {"type": "Point", "coordinates": [76.8957514922814, 10.06656932096729]}, "id": "23", "properties": {"bkt_idx": 6, "bucket": 7, "date": {"type": "Date", "value": 1596673078281}, "ts": 1596673078281.9185, "u": 0.2995227551145926}}, {"type": "Feature", "geometry": {"type": "Point", "coordinates": [77.00469953042143, 9.894207607187886]}, "id": "24", "properties": {"bkt_idx": 4, "bucket": 5, "date": {"type": "Date", "value": 1596672899474}, "ts": 1596672899474.781, "u": 0.24985410580213574}}, {"type": "Feature", "geometry": {"type": "Point", "coordinates": [76.9577468811499, 10.074640853004825]}, "id": "25", "properties": {"bkt_idx": 20, "bucket": 21, "date": {"type": "Date", "value": 1596675274138}, "ts": 1596675274138.7444, "u": 0.9094829845566282}}, {"type": "Feature", "geometry": {"type": "Point", "coordinates": [76.99909622833877, 10.049507240581411]}, "id": "26", "properties": {"bkt_idx": 7, "bucket": 8, "date": {"type": "Date", "value": 1596673347469}, "ts": 1596673347469.9348, "u": 0.3742972041448339}}, {"type": "Feature", "geometry": {"type": "Point", "coordinates": [76.90050434011107, 10.14016492556302]}, "id": "27", "properties": {"bkt_idx": 14, "bucket": 15, "date": {"type": "Date", "value": 1596674330896}, "ts": 1596674330896.7222, "u": 0.6474713117079643}}, {"type": "Feature", "geometry": {"type": "Point", "coordinates": [76.92312349463604, 10.069574848099421]}, "id": "28", "properties": {"bkt_idx": 1, "bucket": 2, "date": {"type": "Date", "value": 1596672423017}, "ts": 1596672423017.426, "u": 0.117504840543599}}, {"type": "Feature", "geometry": {"type": "Point", "coordinates": [76.89081753831493, 10.063859015006692]}, "id": "29", "properties": {"bkt_idx": 13, "bucket": 14, "date": {"type": "Date", "value": 1596674114777}, "ts": 1596674114777.8293, "u": 0.5874382859155866}}, {"type": "Feature", "geometry": {"type": "Point", "coordinates": [76.93188904865494, 10.123868406414898]}, "id": "30", "properties": {"bkt_idx": 11, "bucket": 12, "date": {"type": "Date", "value": 1596673941091}, "ts": 1596673941091.789, "u": 0.5391921636505447}}, {"type": "Feature", "geometry": {"type": "Point", "coordinates": [76.9926032751366, 10.056309463392815]}, "id": "31", "properties": {"bkt_idx": 18, "bucket": 19, "date": {"type": "Date", "value": 1596674966990}, "ts": 1596674966990.4475, "u": 0.8241640132230909}}, {"type": "Feature", "geometry": {"type": "Point", "coordinates": [76.87278616785873, 9.974642948807]}, "id": "32", "properties": {"bkt_idx": 9, "bucket": 10, "date": {"type": "Date", "value": 1596673597086}, "ts": 1596673597086.5625, "u": 0.44363515623138705}}, {"type": "Feature", "geometry": {"type": "Point", "coordinates": [76.92197483838493, 10.049014172712708]}, "id": "33", "properties": {"bkt_idx": 5, "bucket": 6, "date": {"type": "Date", "value": 1596673028745}, "ts": 1596673028745.9114, "u": 0.2857627531834498}}, {"type": "Feature", "geometry": {"type": "Point", "coordinates": [76.95715026137337, 10.066029329392867]}, "id": "34", "properties": {"bkt_idx": 3, "bucket": 4, "date": {"type": "Date", "value": 1596672672194}, "ts": 1596672672194.1438, "u": 0.1867205955216864}}, {"type": "Feature", "geometry": {"type": "Point", "coordinates": [76.8709871296305, 10.073299555423414]}, "id": "35", "properties": {"bkt_idx": 3, "bucket": 4, "date": {"type": "Date", "value": 1596672632704}, "ts": 1596672632704.5115, "u": 0.17575125319105378}}, {"type": "Feature", "geometry": {"type": "Point", "coordinates": [77.06936395820881, 10.073164069232133]}, "id": "36", "properties": {"bkt_idx": 15, "bucket": 16, "date": {"type": "Date", "value": 1596674496741}, "ts": 1596674496741.7307, "u": 0.6935393696315866}}, {"type": "Feature", "geometry": {"type": "Point", "coordinates": [77.02509893475516, 10.104500976977901]}, "id": "37", "properties": {"bkt_idx": 17, "bucket": 18, "date": {"type": "Date", "value": 1596674740749}, "ts": 1596674740749.694, "u": 0.7613193594876079}}, {"type": "Feature", "geometry": {"type": "Point", "coordinates": [76.96839548028471, 9.883775478219034]}, "id": "38", "properties": {"bkt_idx": 7, "bucket": 8, "date": {"type": "Date", "value": 1596673305704}, "ts": 1596673305704.4138, "u": 0.3626956705126202}}, {"type": "Feature", "geometry": {"type": "Point", "coordinates": [76.90394605034145, 10.006517253198139]}, "id": "39", "properties": {"bkt_idx": 5, "bucket": 6, "date": {"type": "Date", "value": 1596672982318}, "ts": 1596672982318.0476, "u": 0.2728661243419884}}, {"type": "Feature", "geometry": {"type": "Point", "coordinates": [76.92208158637186, 10.043518601483415]}, "id": "40", "properties": {"bkt_idx": 18, "bucket": 19, "date": {"type": "Date", "value": 1596674982624}, "ts": 1596674982624.202, "u": 0.8285067227528808}}, {"type": "Feature", "geometry": {"type": "Point", "coordinates": [76.97672439598948, 10.156940487467496]}, "id": "41", "properties": {"bkt_idx": 4, "bucket": 5, "date": {"type": "Date", "value": 1596672764227}, "ts": 1596672764227.5632, "u": 0.2122854342336553}}, {"type": "Feature", "geometry": {"type": "Point", "coordinates": [76.87178747101682, 10.122258470639949]}, "id": "42", "properties": {"bkt_idx": 18, "bucket": 19, "date": {"type": "Date", "value": 1596674858420}, "ts": 1596674858420.2683, "u": 0.7940056300524535}}, {"type": "Feature", "geometry": {"type": "Point", "coordinates": [76.89268297769563, 10.102081819711836]}, "id": "43", "properties": {"bkt_idx": 17, "bucket": 18, "date": {"type": "Date", "value": 1596674791286}, "ts": 1596674791286.6743, "u": 0.7753574095517036}}, {"type": "Feature", "geometry": {"type": "Point", "coordinates": [77.02900812859478, 10.143066580576958]}, "id": "44", "properties": {"bkt_idx": 12, "bucket": 13, "date": {"type": "Date", "value": 1596673973633}, "ts": 1596673973633.5154, "u": 0.5482315320665824}}, {"type": "Feature", "geometry": {"type": "Point", "coordinates": [77.06390647439028, 9.998367015201916]}, "id": "45", "properties": {"bkt_idx": 19, "bucket": 20, "date": {"type": "Date", "value": 1596675003174}, "ts": 1596675003174.3872, "u": 0.8342151075907123}}, {"type": "Feature", "geometry": {"type": "Point", "coordinates": [76.91412227391584, 9.923096528985651]}, "id": "46", "properties": {"bkt_idx": 4, "bucket": 5, "date": {"type": "Date", "value": 1596672887436}, "ts": 1596672887436.7502, "u": 0.24651020838664528}}, {"type": "Feature", "geometry": {"type": "Point", "coordinates": [77.01686362127055, 10.004709498762843]}, "id": "47", "properties": {"bkt_idx": 15, "bucket": 16, "date": {"type": "Date", "value": 1596674513188}, "ts": 1596674513188.3616, "u": 0.6981078782124938}}, {"type": "Feature", "geometry": {"type": "Point", "coordinates": [76.94061059541426, 10.125507170656585]}, "id": "48", "properties": {"bkt_idx": 4, "bucket": 5, "date": {"type": "Date", "value": 1596672752723}, "ts": 1596672752723.3208, "u": 0.20908981136360538}}, {"type": "Feature", "geometry": {"type": "Point", "coordinates": [76.97250629839037, 9.903384916117199]}, "id": "49", "properties": {"bkt_idx": 10, "bucket": 11, "date": {"type": "Date", "value": 1596673652835}, "ts": 1596673652835.7275, "u": 0.4591210354503914}}, {"type": "Feature", "geometry": {"type": "Point", "coordinates": [76.93488520280904, 10.105556371398276]}, "id": "50", "properties": {"bkt_idx": 16, "bucket": 17, "date": {"type": "Date", "value": 1596674689815}, "ts": 1596674689815.0063, "u": 0.7471708350957467}}, {"type": "Feature", "geometry": {"type": "Point", "coordinates": [76.97481658398242, 10.079322978141072]}, "id": "51", "properties": {"bkt_idx": 5, "bucket": 6, "date": {"type": "Date", "value": 1596672981534}, "ts": 1596672981534.8806, "u": 0.2726485779432072}}, {"type": "Feature", "geometry": {"type": "Point", "coordinates": [76.93578991620244, 10.037962270201373]}, "id": "52", "properties": {"bkt_idx": 17, "bucket": 18, "date": {"type": "Date", "value": 1596674823432}, "ts": 1596674823432.0532, "u": 0.7842866814579895}}, {"type": "Feature", "geometry": {"type": "Point", "coordinates": [76.85600688030179, 10.043132103783323]}, "id": "53", "properties": {"bkt_idx": 15, "bucket": 16, "date": {"type": "Date", "value": 1596674538516}, "ts": 1596674538516.6587, "u": 0.70514351632171}}, {"type": "Feature", "geometry": {"type": "Point", "coordinates": [76.99766556286197, 9.962344838915792]}, "id": "54", "properties": {"bkt_idx": 12, "bucket": 13, "date": {"type": "Date", "value": 1596674086130}, "ts": 1596674086130.1614, "u": 0.5794806004041855}}, {"type": "Feature", "geometry": {"type": "Point", "coordinates": [76.90156531447974, 9.957303757226985]}, "id": "55", "properties": {"bkt_idx": 11, "bucket": 12, "date": {"type": "Date", "value": 1596673840034}, "ts": 1596673840034.7915, "u": 0.5111207754379133}}, {"type": "Feature", "geometry": {"type": "Point", "coordinates": [76.83601531376159, 10.007043506221006]}, "id": "56", "properties": {"bkt_idx": 9, "bucket": 10, "date": {"type": "Date", "value": 1596673532363}, "ts": 1596673532363.5078, "u": 0.4256565299361471}}, {"type": "Feature", "geometry": {"type": "Point", "coordinates": [77.05804025262464, 10.002603230802048]}, "id": "57", "properties": {"bkt_idx": 17, "bucket": 18, "date": {"type": "Date", "value": 1596674715375}, "ts": 1596674715375.3132, "u": 0.7542709203409113}}, {"type": "Feature", "geometry": {"type": "Point", "coordinates": [76.93954688784434, 10.023998308090118]}, "id": "58", "properties": {"bkt_idx": 2, "bucket": 3, "date": {"type": "Date", "value": 1596672569264}, "ts": 1596672569264.4163, "u": 0.15812900451004197}}, {"type": "Feature", "geometry": {"type": "Point", "coordinates": [76.99048482446479, 9.964256223694989]}, "id": "59", "properties": {"bkt_idx": 19, "bucket": 20, "date": {"type": "Date", "value": 1596675027594}, "ts": 1596675027594.5278, "u": 0.8409984799594017}}, {"type": "Feature", "geometry": {"type": "Point", "coordinates": [76.97741706901678, 10.023651434745984]}, "id": "60", "properties": {"bkt_idx": 7, "bucket": 8, "date": {"type": "Date", "value": 1596673203420}, "ts": 1596673203420.0159, "u": 0.33428333776666375}}, {"type": "Feature", "geometry": {"type": "Point", "coordinates": [77.0456173844259, 10.14084762449441]}, "id": "61", "properties": {"bkt_idx": 5, "bucket": 6, "date": {"type": "Date", "value": 1596672999041}, "ts": 1596672999041.2354, "u": 0.2775114542314432}}, {"type": "Feature", "geometry": {"type": "Point", "coordinates": [76.92274118424011, 10.03149324790074]}, "id": "62", "properties": {"bkt_idx": 22, "bucket": 23, "date": {"type": "Date", "value": 1596675519023}, "ts": 1596675519023.5935, "u": 0.9775065537501988}}, {"type": "Feature", "geometry": {"type": "Point", "coordinates": [76.96881788836356, 10.033423154589974]}, "id": "63", "properties": {"bkt_idx": 13, "bucket": 14, "date": {"type": "Date", "value": 1596674154829}, "ts": 1596674154829.7378, "u": 0.5985638160433037}}]}